pymilvus_pg-0.1.4.dist-info/METADATA
pymilvus_pg-0.1.4.dist-info/WHEEL
pymilvus_pg-0.1.4.dist-info/entry_points.txt
pymilvus_pg/__init__.py
pymilvus_pg/_version.py
pymilvus_pg/cli.py
pymilvus_pg/exceptions.py
pymilvus_pg/lmdb_manager.py
pymilvus_pg/logger_config.py
pymilvus_pg/milvus_pg_client.py
pymilvus_pg/types.py
pymilvus_pg-0.1.4.dist-info/RECORD
