Metadata-Version: 2.1
Name: pymilvus-pg
Version: 0.1.4
Summary: Sync Milvus data to PostgreSQL for validation
Author-Email: zhuwenxing <wenxing.zhu@zilliz.com>
License: MIT
Requires-Python: >=3.10
Requires-Dist: pymilvus<3.0.0,>=2.5.10
Requires-Dist: psycopg2-binary<3.0.0,>=2.9.9
Requires-Dist: deepdiff<9.0.0,>=8.5.0
Requires-Dist: loguru<1.0.0,>=0.7.0
Requires-Dist: python-dotenv<2.0.0,>=0.19.0
Requires-Dist: click<9.0.0,>=8.0.0
Requires-Dist: lmdb>=1.6.2
Provides-Extra: test
Requires-Dist: pytest>=7.0.0; extra == "test"
Requires-Dist: pytest-asyncio>=0.21.0; extra == "test"
Requires-Dist: pytest-cov>=4.0.0; extra == "test"
Requires-Dist: pytest-mock>=3.10.0; extra == "test"
Provides-Extra: lint
Requires-Dist: ruff>=0.1.0; extra == "lint"
Requires-Dist: mypy>=1.5.0; extra == "lint"
Requires-Dist: pre-commit>=3.0.0; extra == "lint"
